{
  "schema_version": 1,
  "timestamp": "2026-07-18T07:57:25Z",
  "asset": "cUSD",
  "chain": "ethereum",
  "data_source": "complete",
  "summary": {
    "asset": "cUSD",
    "total_supply": 71409863.2868663,
    "total_backing": 71396192.94449688,
    "coverage_ratio": 0.9998085650673422,
    "coverage_pct": 99.98085650673421,
    "total_borrows_usd": 39380911.841701634,
    "max_utilization": 0.5939510517317467,
    "stcusd_supply": 58463700.12528304,
    "stcusd_total_assets": 62625875.18098331,
    "stcusd_nav": 1.071192467236611,
    "operator_count": 42,
    "operator_material_count": 15,
    "operator_worst_health": 1.4749327129419594,
    "operator_dust_worst_health": 0.12238579488622048,
    "operator_health_min_debt_usd": 10000.0
  },
  "backing_breakdown": [
    {
      "name": "USDC",
      "amount": 66315924.94059,
      "value_usd": 66303295.07268507,
      "pct": 92.86670946758882,
      "source": "Vault.totalSupplies + Oracle.getPrice"
    },
    {
      "name": "wWTGXX",
      "amount": 5092897.871811816,
      "value_usd": 5092897.871811816,
      "pct": 7.133290532411181,
      "source": "Vault.totalSupplies + Oracle.getPrice"
    }
  ],
  "risk_flags": [
    {
      "id": "reserve_concentration",
      "severity": "info",
      "message": "USDC is 92.9% of reserve value",
      "value": 92.86670946758882
    }
  ],
  "asset_specific": {
    "vault_state": {
      "address": "0xcCcc62962d17b8914c62D74FfB843d73B2a3cccC",
      "reserves": [
        {
          "asset": "0xA0b86991c6218b36c1d19D4a2e9Eb0cE3606eB48",
          "symbol": "USDC",
          "decimals": 6,
          "oracle_price_usd": 0.99980955,
          "oracle_last_updated": 1784279351,
          "total_supplies": 66315924.94059,
          "total_supplies_usd": 66303295.07268507,
          "total_borrows": 39388413.365027,
          "total_borrows_usd": 39380911.841701634,
          "available_balance": 26927511.575563,
          "available_balance_usd": 26922383.230983432,
          "utilization": 0.5939510517317467,
          "utilization_pct": 59.39510517317467,
          "idle_reserve_target": 0.0,
          "loaned_to_fractional_reserve": 26927507.798061,
          "fractional_reserve_vault": "0x3Ed6aa32c930253fc990dE58fF882B9186cd0072",
          "fractional_reserve_vault_set": true,
          "benchmark_rate_apy": 0.034999999999999996,
          "utilization_rate_apy": 0.017818414257336858,
          "lender_reserve": {
            "id": 0,
            "vault": "0xcCcc62962d17b8914c62D74FfB843d73B2a3cccC",
            "debt_token": "0xfa8C6D0b95d9191B5A1D51C868Da2BDFd6C04Ff9",
            "interest_receiver": "0xa1a20aBdc873CF291c22Ce3C8968EC06277324D0",
            "decimals": 6,
            "paused": false,
            "min_borrow": 100.0
          },
          "pct_of_reserves": 92.86670946758882,
          "deployed_pct": 40.604889130603794
        },
        {
          "asset": "0x434558CB1EBe9950e8A66f1ef8A15A473Dce7D8c",
          "symbol": "wWTGXX",
          "decimals": 18,
          "oracle_price_usd": 1.0,
          "oracle_last_updated": 1784361371,
          "total_supplies": 5092897.871811816,
          "total_supplies_usd": 5092897.871811816,
          "total_borrows": 0.0,
          "total_borrows_usd": 0.0,
          "available_balance": 5092897.871811816,
          "available_balance_usd": 5092897.871811816,
          "utilization": 0.0,
          "utilization_pct": 0.0,
          "idle_reserve_target": 0.0,
          "loaned_to_fractional_reserve": 5092033.265897586,
          "fractional_reserve_vault": "0xb1c1C80FDbBde5B40264e1410550F3C864113bF8",
          "fractional_reserve_vault_set": true,
          "benchmark_rate_apy": 0.0,
          "utilization_rate_apy": null,
          "lender_reserve": {
            "id": 0,
            "vault": "0x0000000000000000000000000000000000000000",
            "debt_token": "0x0000000000000000000000000000000000000000",
            "interest_receiver": "0x0000000000000000000000000000000000000000",
            "decimals": 0,
            "paused": false,
            "min_borrow": 0.0
          },
          "pct_of_reserves": 7.133290532411181,
          "deployed_pct": 99.98302330154675
        }
      ],
      "coverage_ratio": 0.9998085650673422,
      "utilization_by_asset": [
        {
          "symbol": "USDC",
          "utilization": 0.5939510517317467,
          "utilization_pct": 59.39510517317467
        },
        {
          "symbol": "wWTGXX",
          "utilization": 0.0,
          "utilization_pct": 0.0
        }
      ]
    },
    "peg": {
      "market_price": 0.9998,
      "theoretical_price": 1.0,
      "deviation_bps": -2.0,
      "quotes": [
        {
          "pool": "eth_0x755ba79de3efc0cf4709fe28b78cb7268aa408f9b565ad10e13f3a59702b5ff6",
          "price_usd": 0.9664100072,
          "volume_24h_usd": 48.8181586658,
          "liquidity_usd": 3878.2982,
          "dex": "",
          "source": "geckoterminal",
          "fetch_status": "ok",
          "liquidity_thin": true,
          "pool_count": 16
        },
        {
          "source": "coingecko",
          "fetch_status": "ok",
          "price_usd": 0.999836,
          "volume_24h_usd": 48.8398630734,
          "liquidity_thin": true
        },
        {
          "source": "bathymark",
          "fetch_status": "ok",
          "price_usd": 0.9998
        }
      ],
      "liquidity_thin": false,
      "usable_quote_count": 3,
      "non_thin_quote_count": 1,
      "agreeing_offpeg_quote_count": 1,
      "peg_signal_gated": true,
      "source": "geckoterminal+coingecko+bathymark"
    },
    "operator_book": {
      "source": "delegation_agents_getter",
      "operators": [
        {
          "agent": "0x00b6aCF0FD8d742a0DbE75048dEa85cBf5Cb2eFE",
          "label": null,
          "fetch_status": "ok",
          "total_delegation_usd": 498599.94030303,
          "total_slashable_collateral_usd": 498599.94030303,
          "total_debt_usd": 104056.7966231,
          "ltv": 0.20869797248643523,
          "liquidation_threshold": 0.8,
          "health_factor": 3.833290714177866,
          "delegation_coverage_usd": 498599.94030303,
          "slashable_collateral_usd": 498599.94030303,
          "detail_fetch_status": "aggregate_only",
          "detail_note": "Hourly path uses Lender.agent() aggregates for all agents; per-asset debt and network/collateral detail are intentionally not fanned out."
        },
        {
          "agent": "0x0D35D950FDb0741F11c4384dAd15A07EdB26E21A",
          "label": null,
          "fetch_status": "ok",
          "total_delegation_usd": 327.63453606,
          "total_slashable_collateral_usd": 327.63453606,
          "total_debt_usd": 198.29117026,
          "ltv": 0.6052205992828752,
          "liquidation_threshold": 0.8,
          "health_factor": 1.3218320740370015,
          "delegation_coverage_usd": 327.63453606,
          "slashable_collateral_usd": 327.63453606,
          "detail_fetch_status": "aggregate_only",
          "detail_note": "Hourly path uses Lender.agent() aggregates for all agents; per-asset debt and network/collateral detail are intentionally not fanned out."
        },
        {
          "agent": "0x10e7FEA8b043d5e3Bd49e5028B4651D67f8F6B9F",
          "label": null,
          "fetch_status": "ok",
          "total_delegation_usd": 0.0,
          "total_slashable_collateral_usd": 0.0,
          "total_debt_usd": 0.0,
          "ltv": 0.0,
          "liquidation_threshold": 0.8,
          "health_factor": 1.157920892373162e+50,
          "delegation_coverage_usd": 0.0,
          "slashable_collateral_usd": 0.0,
          "detail_fetch_status": "aggregate_only",
          "detail_note": "Hourly path uses Lender.agent() aggregates for all agents; per-asset debt and network/collateral detail are intentionally not fanned out."
        },
        {
          "agent": "0x1391BcF14ec26efe3780BD787061fD932a8b4134",
          "label": null,
          "fetch_status": "ok",
          "total_delegation_usd": 644.44235676,
          "total_slashable_collateral_usd": 644.44235676,
          "total_debt_usd": 0.0,
          "ltv": 0.0,
          "liquidation_threshold": 0.8,
          "health_factor": 1.157920892373162e+50,
          "delegation_coverage_usd": 644.44235676,
          "slashable_collateral_usd": 644.44235676,
          "detail_fetch_status": "aggregate_only",
          "detail_note": "Hourly path uses Lender.agent() aggregates for all agents; per-asset debt and network/collateral detail are intentionally not fanned out."
        },
        {
          "agent": "0x151039298262FAd60c28277d5332873f44f46151",
          "label": null,
          "fetch_status": "ok",
          "total_delegation_usd": 0.57556068,
          "total_slashable_collateral_usd": 0.57556068,
          "total_debt_usd": 0.0,
          "ltv": 0.0,
          "liquidation_threshold": 0.8,
          "health_factor": 1.157920892373162e+50,
          "delegation_coverage_usd": 0.57556068,
          "slashable_collateral_usd": 0.57556068,
          "detail_fetch_status": "aggregate_only",
          "detail_note": "Hourly path uses Lender.agent() aggregates for all agents; per-asset debt and network/collateral detail are intentionally not fanned out."
        },
        {
          "agent": "0x20a9c004dE10D372ff021752083c8Cc8996550C1",
          "label": null,
          "fetch_status": "ok",
          "total_delegation_usd": 204.64379932,
          "total_slashable_collateral_usd": 204.64379932,
          "total_debt_usd": 0.0,
          "ltv": 0.0,
          "liquidation_threshold": 0.8,
          "health_factor": 1.157920892373162e+50,
          "delegation_coverage_usd": 204.64379932,
          "slashable_collateral_usd": 204.64379932,
          "detail_fetch_status": "aggregate_only",
          "detail_note": "Hourly path uses Lender.agent() aggregates for all agents; per-asset debt and network/collateral detail are intentionally not fanned out."
        },
        {
          "agent": "0x2bD06CcbBF36973447Bedc14149c47a13E466Ca9",
          "label": null,
          "fetch_status": "ok",
          "total_delegation_usd": 0.0,
          "total_slashable_collateral_usd": 0.0,
          "total_debt_usd": 0.0,
          "ltv": 0.0,
          "liquidation_threshold": 0.8,
          "health_factor": 1.157920892373162e+50,
          "delegation_coverage_usd": 0.0,
          "slashable_collateral_usd": 0.0,
          "detail_fetch_status": "aggregate_only",
          "detail_note": "Hourly path uses Lender.agent() aggregates for all agents; per-asset debt and network/collateral detail are intentionally not fanned out."
        },
        {
          "agent": "0x3fA0d4Ce8c396B03beB3D8411e10b0126A1B913d",
          "label": null,
          "fetch_status": "ok",
          "total_delegation_usd": 16063017.91115837,
          "total_slashable_collateral_usd": 16063017.91115837,
          "total_debt_usd": 6895090.24570586,
          "ltv": 0.4292524781981412,
          "liquidation_threshold": 0.8,
          "health_factor": 1.863705023575247,
          "delegation_coverage_usd": 16063017.91115837,
          "slashable_collateral_usd": 16063017.91115837,
          "detail_fetch_status": "aggregate_only",
          "detail_note": "Hourly path uses Lender.agent() aggregates for all agents; per-asset debt and network/collateral detail are intentionally not fanned out."
        },
        {
          "agent": "0x4Cd7C473985Ca1399810536e0482dF1e4E0672D6",
          "label": null,
          "fetch_status": "ok",
          "total_delegation_usd": 12437658.80524258,
          "total_slashable_collateral_usd": 12437658.80524258,
          "total_debt_usd": 4741234.77509204,
          "ltv": 0.38119993877735,
          "liquidation_threshold": 0.8,
          "health_factor": 2.098636223725265,
          "delegation_coverage_usd": 12437658.80524258,
          "slashable_collateral_usd": 12437658.80524258,
          "detail_fetch_status": "aggregate_only",
          "detail_note": "Hourly path uses Lender.agent() aggregates for all agents; per-asset debt and network/collateral detail are intentionally not fanned out."
        },
        {
          "agent": "0x4d7B27e0f5D85e41870FE7E680c347bc943231aF",
          "label": null,
          "fetch_status": "ok",
          "total_delegation_usd": 498599.94030303,
          "total_slashable_collateral_usd": 498599.94030303,
          "total_debt_usd": 238547.81077438,
          "ltv": 0.4784352975040465,
          "liquidation_threshold": 0.8,
          "health_factor": 1.6721174298249466,
          "delegation_coverage_usd": 498599.94030303,
          "slashable_collateral_usd": 498599.94030303,
          "detail_fetch_status": "aggregate_only",
          "detail_note": "Hourly path uses Lender.agent() aggregates for all agents; per-asset debt and network/collateral detail are intentionally not fanned out."
        },
        {
          "agent": "0x53dF43d7F5de0B80d64F54648AED460EB8F74b2C",
          "label": null,
          "fetch_status": "ok",
          "total_delegation_usd": 0.0,
          "total_slashable_collateral_usd": 0.0,
          "total_debt_usd": 0.0,
          "ltv": 0.0,
          "liquidation_threshold": 0.8,
          "health_factor": 1.157920892373162e+50,
          "delegation_coverage_usd": 0.0,
          "slashable_collateral_usd": 0.0,
          "detail_fetch_status": "aggregate_only",
          "detail_note": "Hourly path uses Lender.agent() aggregates for all agents; per-asset debt and network/collateral detail are intentionally not fanned out."
        },
        {
          "agent": "0x5f33ff3027c4763D36e6f4F7C20eE72F700A5D34",
          "label": null,
          "fetch_status": "ok",
          "total_delegation_usd": 498599.94030303,
          "total_slashable_collateral_usd": 498599.94030303,
          "total_debt_usd": 235132.42099327,
          "ltv": 0.47158533723523005,
          "liquidation_threshold": 0.8,
          "health_factor": 1.6964055852333557,
          "delegation_coverage_usd": 498599.94030303,
          "slashable_collateral_usd": 498599.94030303,
          "detail_fetch_status": "aggregate_only",
          "detail_note": "Hourly path uses Lender.agent() aggregates for all agents; per-asset debt and network/collateral detail are intentionally not fanned out."
        },
        {
          "agent": "0x616CC67eF3fEeA3a584CcD100a975763dc7F9F42",
          "label": null,
          "fetch_status": "ok",
          "total_delegation_usd": 200990.8293,
          "total_slashable_collateral_usd": 200990.8293,
          "total_debt_usd": 109016.94838626,
          "ltv": 0.5423976246375933,
          "liquidation_threshold": 0.8,
          "health_factor": 1.4749327129419594,
          "delegation_coverage_usd": 200990.8293,
          "slashable_collateral_usd": 200990.8293,
          "detail_fetch_status": "aggregate_only",
          "detail_note": "Hourly path uses Lender.agent() aggregates for all agents; per-asset debt and network/collateral detail are intentionally not fanned out."
        },
        {
          "agent": "0x624C31fdFB9CcbAF182a3c503Cf245BCa671b860",
          "label": null,
          "fetch_status": "ok",
          "total_delegation_usd": 8340256.40614935,
          "total_slashable_collateral_usd": 8340256.40614935,
          "total_debt_usd": 3409504.62061962,
          "ltv": 0.40880093543715995,
          "liquidation_threshold": 0.8,
          "health_factor": 1.9569426844498363,
          "delegation_coverage_usd": 8340256.40614935,
          "slashable_collateral_usd": 8340256.40614935,
          "detail_fetch_status": "aggregate_only",
          "detail_note": "Hourly path uses Lender.agent() aggregates for all agents; per-asset debt and network/collateral detail are intentionally not fanned out."
        },
        {
          "agent": "0x653d5c6CEf72822e7C409ecB5c46C5c2858E5F2A",
          "label": null,
          "fetch_status": "ok",
          "total_delegation_usd": 0.0,
          "total_slashable_collateral_usd": 0.0,
          "total_debt_usd": 0.0,
          "ltv": 0.0,
          "liquidation_threshold": 0.8,
          "health_factor": 1.157920892373162e+50,
          "delegation_coverage_usd": 0.0,
          "slashable_collateral_usd": 0.0,
          "detail_fetch_status": "aggregate_only",
          "detail_note": "Hourly path uses Lender.agent() aggregates for all agents; per-asset debt and network/collateral detail are intentionally not fanned out."
        },
        {
          "agent": "0x670d254d23F4B9413E02BB98a87163Fd27A5A9C9",
          "label": null,
          "fetch_status": "ok",
          "total_delegation_usd": 0.0,
          "total_slashable_collateral_usd": 0.0,
          "total_debt_usd": 0.0,
          "ltv": 0.0,
          "liquidation_threshold": 0.8,
          "health_factor": 1.157920892373162e+50,
          "delegation_coverage_usd": 0.0,
          "slashable_collateral_usd": 0.0,
          "detail_fetch_status": "aggregate_only",
          "detail_note": "Hourly path uses Lender.agent() aggregates for all agents; per-asset debt and network/collateral detail are intentionally not fanned out."
        },
        {
          "agent": "0x67b1153dc2EAd7D45668edBd8BAF11A839a9136e",
          "label": null,
          "fetch_status": "ok",
          "total_delegation_usd": 0.0,
          "total_slashable_collateral_usd": 0.0,
          "total_debt_usd": 0.0,
          "ltv": 0.0,
          "liquidation_threshold": 0.8,
          "health_factor": 1.157920892373162e+50,
          "delegation_coverage_usd": 0.0,
          "slashable_collateral_usd": 0.0,
          "detail_fetch_status": "aggregate_only",
          "detail_note": "Hourly path uses Lender.agent() aggregates for all agents; per-asset debt and network/collateral detail are intentionally not fanned out."
        },
        {
          "agent": "0x69A6Af78fc45F654A1b5feEbC22c1fee88Df8a8F",
          "label": null,
          "fetch_status": "ok",
          "total_delegation_usd": 498599.94030303,
          "total_slashable_collateral_usd": 498599.94030303,
          "total_debt_usd": 213232.55342853,
          "ltv": 0.42766261323444077,
          "liquidation_threshold": 0.8,
          "health_factor": 1.8706334742463149,
          "delegation_coverage_usd": 498599.94030303,
          "slashable_collateral_usd": 498599.94030303,
          "detail_fetch_status": "aggregate_only",
          "detail_note": "Hourly path uses Lender.agent() aggregates for all agents; per-asset debt and network/collateral detail are intentionally not fanned out."
        },
        {
          "agent": "0x6B82fFdfbc3DC0d0E394a0930229BA98EaC43a46",
          "label": null,
          "fetch_status": "ok",
          "total_delegation_usd": 314.16998472,
          "total_slashable_collateral_usd": 314.16998472,
          "total_debt_usd": 0.0,
          "ltv": 0.0,
          "liquidation_threshold": 0.85,
          "health_factor": 1.157920892373162e+50,
          "delegation_coverage_usd": 314.16998472,
          "slashable_collateral_usd": 314.16998472,
          "detail_fetch_status": "aggregate_only",
          "detail_note": "Hourly path uses Lender.agent() aggregates for all agents; per-asset debt and network/collateral detail are intentionally not fanned out."
        },
        {
          "agent": "0x6E27837Dcd6BCCf9484594066de2E89DeA209B28",
          "label": null,
          "fetch_status": "ok",
          "total_delegation_usd": 0.0,
          "total_slashable_collateral_usd": 0.0,
          "total_debt_usd": 0.0,
          "ltv": 0.0,
          "liquidation_threshold": 0.8,
          "health_factor": 1.157920892373162e+50,
          "delegation_coverage_usd": 0.0,
          "slashable_collateral_usd": 0.0,
          "detail_fetch_status": "aggregate_only",
          "detail_note": "Hourly path uses Lender.agent() aggregates for all agents; per-asset debt and network/collateral detail are intentionally not fanned out."
        },
        {
          "agent": "0x6f349c02CdbfCA93B315B026Ecd7B0416C46D5e8",
          "label": null,
          "fetch_status": "ok",
          "total_delegation_usd": 1.094752,
          "total_slashable_collateral_usd": 1.094752,
          "total_debt_usd": 0.0,
          "ltv": 0.0,
          "liquidation_threshold": 0.85,
          "health_factor": 1.157920892373162e+50,
          "delegation_coverage_usd": 1.094752,
          "slashable_collateral_usd": 1.094752,
          "detail_fetch_status": "aggregate_only",
          "detail_note": "Hourly path uses Lender.agent() aggregates for all agents; per-asset debt and network/collateral detail are intentionally not fanned out."
        },
        {
          "agent": "0x76d266DFD3754f090488ae12F6Bd115cD7E77eBD",
          "label": null,
          "fetch_status": "ok",
          "total_delegation_usd": 20.55679287,
          "total_slashable_collateral_usd": 20.55679287,
          "total_debt_usd": 0.0,
          "ltv": 0.0,
          "liquidation_threshold": 0.8,
          "health_factor": 1.157920892373162e+50,
          "delegation_coverage_usd": 20.55679287,
          "slashable_collateral_usd": 20.55679287,
          "detail_fetch_status": "aggregate_only",
          "detail_note": "Hourly path uses Lender.agent() aggregates for all agents; per-asset debt and network/collateral detail are intentionally not fanned out."
        },
        {
          "agent": "0x77df7B5aBF875894Ffb1443Fd2840b603d3AC1DA",
          "label": null,
          "fetch_status": "ok",
          "total_delegation_usd": 103.93409555,
          "total_slashable_collateral_usd": 103.93409555,
          "total_debt_usd": 679.38666017,
          "ltv": 6.536706328898246,
          "liquidation_threshold": 0.8,
          "health_factor": 0.12238579488622048,
          "delegation_coverage_usd": 103.93409555,
          "slashable_collateral_usd": 103.93409555,
          "detail_fetch_status": "aggregate_only",
          "detail_note": "Hourly path uses Lender.agent() aggregates for all agents; per-asset debt and network/collateral detail are intentionally not fanned out."
        },
        {
          "agent": "0x7F2165014A477f6ABA532000d8088Ed64dD1eBA1",
          "label": null,
          "fetch_status": "ok",
          "total_delegation_usd": 4674840.66498135,
          "total_slashable_collateral_usd": 6340050.84326237,
          "total_debt_usd": 2248749.04602482,
          "ltv": 0.48103223343416157,
          "liquidation_threshold": 0.8,
          "health_factor": 1.66309021391078,
          "delegation_coverage_usd": 4674840.66498135,
          "slashable_collateral_usd": 6340050.84326237,
          "detail_fetch_status": "aggregate_only",
          "detail_note": "Hourly path uses Lender.agent() aggregates for all agents; per-asset debt and network/collateral detail are intentionally not fanned out."
        },
        {
          "agent": "0x8085f146525E8A20B98187Eb64Ad46f79f0d8Ef6",
          "label": null,
          "fetch_status": "ok",
          "total_delegation_usd": 195.37087717,
          "total_slashable_collateral_usd": 195.37087717,
          "total_debt_usd": 107.90393079,
          "ltv": 0.5523030471737529,
          "liquidation_threshold": 0.8,
          "health_factor": 1.4484801488852228,
          "delegation_coverage_usd": 195.37087717,
          "slashable_collateral_usd": 195.37087717,
          "detail_fetch_status": "aggregate_only",
          "detail_note": "Hourly path uses Lender.agent() aggregates for all agents; per-asset debt and network/collateral detail are intentionally not fanned out."
        },
        {
          "agent": "0x83355D6AdbfCaA7b6e81e7EBc31393744ADa0fF9",
          "label": null,
          "fetch_status": "ok",
          "total_delegation_usd": 0.0,
          "total_slashable_collateral_usd": 0.0,
          "total_debt_usd": 0.0,
          "ltv": 0.0,
          "liquidation_threshold": 0.8,
          "health_factor": 1.157920892373162e+50,
          "delegation_coverage_usd": 0.0,
          "slashable_collateral_usd": 0.0,
          "detail_fetch_status": "aggregate_only",
          "detail_note": "Hourly path uses Lender.agent() aggregates for all agents; per-asset debt and network/collateral detail are intentionally not fanned out."
        },
        {
          "agent": "0x88D09e8F4F889a9dCa4Fcb4de18B3AF5856d8D4b",
          "label": null,
          "fetch_status": "ok",
          "total_delegation_usd": 0.0,
          "total_slashable_collateral_usd": 0.0,
          "total_debt_usd": 0.0,
          "ltv": 0.0,
          "liquidation_threshold": 0.8,
          "health_factor": 1.157920892373162e+50,
          "delegation_coverage_usd": 0.0,
          "slashable_collateral_usd": 0.0,
          "detail_fetch_status": "aggregate_only",
          "detail_note": "Hourly path uses Lender.agent() aggregates for all agents; per-asset debt and network/collateral detail are intentionally not fanned out."
        },
        {
          "agent": "0x89718378C3E5E97eEde85728d43fc4cE3Ef18774",
          "label": null,
          "fetch_status": "ok",
          "total_delegation_usd": 188.54544437,
          "total_slashable_collateral_usd": 188.54544437,
          "total_debt_usd": 107.88790984,
          "ltv": 0.5722117031280887,
          "liquidation_threshold": 0.8,
          "health_factor": 1.3980839532408535,
          "delegation_coverage_usd": 188.54544437,
          "slashable_collateral_usd": 188.54544437,
          "detail_fetch_status": "aggregate_only",
          "detail_note": "Hourly path uses Lender.agent() aggregates for all agents; per-asset debt and network/collateral detail are intentionally not fanned out."
        },
        {
          "agent": "0x89Ffc736225bbfaA18aC20a846203CDbe7cC67D6",
          "label": null,
          "fetch_status": "ok",
          "total_delegation_usd": 498599.94030303,
          "total_slashable_collateral_usd": 498599.94030303,
          "total_debt_usd": 223839.36518744,
          "ltv": 0.4489358042269299,
          "liquidation_threshold": 0.8,
          "health_factor": 1.7819919740587515,
          "delegation_coverage_usd": 498599.94030303,
          "slashable_collateral_usd": 498599.94030303,
          "detail_fetch_status": "aggregate_only",
          "detail_note": "Hourly path uses Lender.agent() aggregates for all agents; per-asset debt and network/collateral detail are intentionally not fanned out."
        },
        {
          "agent": "0x9F878a84e6F55607501160b92536C6D40109EC3A",
          "label": null,
          "fetch_status": "ok",
          "total_delegation_usd": 315.7644404,
          "total_slashable_collateral_usd": 315.7644404,
          "total_debt_usd": 0.0,
          "ltv": 0.0,
          "liquidation_threshold": 0.85,
          "health_factor": 1.157920892373162e+50,
          "delegation_coverage_usd": 315.7644404,
          "slashable_collateral_usd": 315.7644404,
          "detail_fetch_status": "aggregate_only",
          "detail_note": "Hourly path uses Lender.agent() aggregates for all agents; per-asset debt and network/collateral detail are intentionally not fanned out."
        },
        {
          "agent": "0xa5C5d09a2Ac3460DeAA5510CbB74F85BCd1f254E",
          "label": null,
          "fetch_status": "ok",
          "total_delegation_usd": 2825598.16859154,
          "total_slashable_collateral_usd": 2825598.16859154,
          "total_debt_usd": 1182957.68262388,
          "ltv": 0.41865743536121497,
          "liquidation_threshold": 0.8,
          "health_factor": 1.9108701588203376,
          "delegation_coverage_usd": 2825598.16859154,
          "slashable_collateral_usd": 2825598.16859154,
          "detail_fetch_status": "aggregate_only",
          "detail_note": "Hourly path uses Lender.agent() aggregates for all agents; per-asset debt and network/collateral detail are intentionally not fanned out."
        },
        {
          "agent": "0xa61F7f64F4e4B8E919DccfBE0dc5aa903e2c0Cca",
          "label": null,
          "fetch_status": "ok",
          "total_delegation_usd": 0.0,
          "total_slashable_collateral_usd": 0.0,
          "total_debt_usd": 0.0,
          "ltv": 0.0,
          "liquidation_threshold": 0.8,
          "health_factor": 1.157920892373162e+50,
          "delegation_coverage_usd": 0.0,
          "slashable_collateral_usd": 0.0,
          "detail_fetch_status": "aggregate_only",
          "detail_note": "Hourly path uses Lender.agent() aggregates for all agents; per-asset debt and network/collateral detail are intentionally not fanned out."
        },
        {
          "agent": "0xaCaaF5AAc016257BF305640fc7D7239648A0D34A",
          "label": null,
          "fetch_status": "ok",
          "total_delegation_usd": 2555293.97986249,
          "total_slashable_collateral_usd": 2555293.97986249,
          "total_debt_usd": 1261359.43206143,
          "ltv": 0.49362595537023435,
          "liquidation_threshold": 0.8,
          "health_factor": 1.6206603224499732,
          "delegation_coverage_usd": 2555293.97986249,
          "slashable_collateral_usd": 2555293.97986249,
          "detail_fetch_status": "aggregate_only",
          "detail_note": "Hourly path uses Lender.agent() aggregates for all agents; per-asset debt and network/collateral detail are intentionally not fanned out."
        },
        {
          "agent": "0xbAfa91d22C093E42E28D7Be417e38244E4153f78",
          "label": "Bedrock CAP operator",
          "fetch_status": "ok",
          "total_delegation_usd": 65760908.30079519,
          "total_slashable_collateral_usd": 65760908.30079519,
          "total_debt_usd": 17059807.84521127,
          "ltv": 0.259421718556235,
          "liquidation_threshold": 0.8,
          "health_factor": 3.0837818994194333,
          "delegation_coverage_usd": 65760908.30079519,
          "slashable_collateral_usd": 65760908.30079519,
          "detail_fetch_status": "aggregate_only",
          "detail_note": "Hourly path uses Lender.agent() aggregates for all agents; per-asset debt and network/collateral detail are intentionally not fanned out."
        },
        {
          "agent": "0xc1ab5a9593E6e1662A9a44F84Df4F31Fc8A76B52",
          "label": null,
          "fetch_status": "ok",
          "total_delegation_usd": 0.0,
          "total_slashable_collateral_usd": 0.0,
          "total_debt_usd": 0.0,
          "ltv": 0.0,
          "liquidation_threshold": 0.8,
          "health_factor": 1.157920892373162e+50,
          "delegation_coverage_usd": 0.0,
          "slashable_collateral_usd": 0.0,
          "detail_fetch_status": "aggregate_only",
          "detail_note": "Hourly path uses Lender.agent() aggregates for all agents; per-asset debt and network/collateral detail are intentionally not fanned out."
        },
        {
          "agent": "0xd32147536a86D0ff48ca6FAC028180AE8f39b84d",
          "label": null,
          "fetch_status": "ok",
          "total_delegation_usd": 0.0,
          "total_slashable_collateral_usd": 0.0,
          "total_debt_usd": 0.0,
          "ltv": 0.0,
          "liquidation_threshold": 0.8,
          "health_factor": 1.157920892373162e+50,
          "delegation_coverage_usd": 0.0,
          "slashable_collateral_usd": 0.0,
          "detail_fetch_status": "aggregate_only",
          "detail_note": "Hourly path uses Lender.agent() aggregates for all agents; per-asset debt and network/collateral detail are intentionally not fanned out."
        },
        {
          "agent": "0xd418224aE3c510B645112FD9275CCFD50F996ee4",
          "label": null,
          "fetch_status": "ok",
          "total_delegation_usd": 0.0,
          "total_slashable_collateral_usd": 0.0,
          "total_debt_usd": 0.0,
          "ltv": 0.0,
          "liquidation_threshold": 0.8,
          "health_factor": 1.157920892373162e+50,
          "delegation_coverage_usd": 0.0,
          "slashable_collateral_usd": 0.0,
          "detail_fetch_status": "aggregate_only",
          "detail_note": "Hourly path uses Lender.agent() aggregates for all agents; per-asset debt and network/collateral detail are intentionally not fanned out."
        },
        {
          "agent": "0xdeBecd97c5E91463472CD4396250EfE1cb33c21e",
          "label": null,
          "fetch_status": "ok",
          "total_delegation_usd": 90524439.31514663,
          "total_slashable_collateral_usd": 90524439.31514663,
          "total_debt_usd": 0.0,
          "ltv": 0.0,
          "liquidation_threshold": 0.8,
          "health_factor": 1.157920892373162e+50,
          "delegation_coverage_usd": 90524439.31514663,
          "slashable_collateral_usd": 90524439.31514663,
          "detail_fetch_status": "aggregate_only",
          "detail_note": "Hourly path uses Lender.agent() aggregates for all agents; per-asset debt and network/collateral detail are intentionally not fanned out."
        },
        {
          "agent": "0xe76F8b47dB23789C08e3D761AF0F74C403dB8Bb9",
          "label": null,
          "fetch_status": "ok",
          "total_delegation_usd": 2110393.9909783,
          "total_slashable_collateral_usd": 2110393.9909783,
          "total_debt_usd": 1007518.38774419,
          "ltv": 0.4774077219946698,
          "liquidation_threshold": 0.8,
          "health_factor": 1.6757165063386468,
          "delegation_coverage_usd": 2110393.9909783,
          "slashable_collateral_usd": 2110393.9909783,
          "detail_fetch_status": "aggregate_only",
          "detail_note": "Hourly path uses Lender.agent() aggregates for all agents; per-asset debt and network/collateral detail are intentionally not fanned out."
        },
        {
          "agent": "0xe916c5046AC2A29Db3D6442f0b6a4B7CE2D80F2c",
          "label": null,
          "fetch_status": "ok",
          "total_delegation_usd": 838464.16070247,
          "total_slashable_collateral_usd": 839049.6396791,
          "total_debt_usd": 111.18996884,
          "ltv": 0.00013261147470733207,
          "liquidation_threshold": 0.8,
          "health_factor": 6032.660459930533,
          "delegation_coverage_usd": 838464.16070247,
          "slashable_collateral_usd": 839049.6396791,
          "detail_fetch_status": "aggregate_only",
          "detail_note": "Hourly path uses Lender.agent() aggregates for all agents; per-asset debt and network/collateral detail are intentionally not fanned out."
        },
        {
          "agent": "0xF932130Fabb5A2383C054a4c8eac59Cf1Ced570c",
          "label": null,
          "fetch_status": "ok",
          "total_delegation_usd": 2284088.09737,
          "total_slashable_collateral_usd": 2284088.09737,
          "total_debt_usd": 0.0,
          "ltv": 0.0,
          "liquidation_threshold": 0.8,
          "health_factor": 1.157920892373162e+50,
          "delegation_coverage_usd": 2284088.09737,
          "slashable_collateral_usd": 2284088.09737,
          "detail_fetch_status": "aggregate_only",
          "detail_note": "Hourly path uses Lender.agent() aggregates for all agents; per-asset debt and network/collateral detail are intentionally not fanned out."
        },
        {
          "agent": "0xFb3bD022D5DAcF95eE28a6B07825D4Ff9C5b3814",
          "label": null,
          "fetch_status": "ok",
          "total_delegation_usd": 1175319.27543675,
          "total_slashable_collateral_usd": 1175319.27543675,
          "total_debt_usd": 476197.21633662,
          "ltv": 0.4051641339411068,
          "liquidation_threshold": 0.8,
          "health_factor": 1.9745084349353712,
          "delegation_coverage_usd": 1175319.27543675,
          "slashable_collateral_usd": 1175319.27543675,
          "detail_fetch_status": "aggregate_only",
          "detail_note": "Hourly path uses Lender.agent() aggregates for all agents; per-asset debt and network/collateral detail are intentionally not fanned out."
        }
      ],
      "failed_operators": []
    },
    "restaker_coverage": {
      "total_coverage_usd": 212286586.33987007,
      "total_slashable_collateral_usd": 213952381.9971277,
      "total_debt_usd": 39407449.80645261,
      "coverage_to_debt_ratio": 5.386965849921861,
      "symbiotic_only_v1": true,
      "eigenlayer": {
        "status": "deferred",
        "reason": "service-manager mapping not confirmed for v1"
      }
    }
  }
}