{
  "schema_version": 1,
  "asset": "sUSDai",
  "asset_slug": "susdai",
  "chain": "arbitrum",
  "timestamp": "2026-06-03T02:44:09Z",
  "as_of": "2026-06-03T02:44:09Z",
  "block_number": 469477792,
  "summary": {
    "total_assets_usd": 300546332.06,
    "share_supply": 168504345.897081,
    "nav_per_share": 1.088769,
    "buffer_ratio": 0.174163,
    "idle_usdai_usd": 52344083.78,
    "deposit_timelock_escrow_usd": 140009710.21,
    "implied_deployed_loans_usd": 104152040.42,
    "recon_residual_pct": 0.010446,
    "peg_secondary_px": 1.085457,
    "discount_to_nav_pct": 0.3042,
    "paused": false,
    "implementation": "0x5F02C1Bec4Ad5dE9b7Abf999C1F0854d4836a049",
    "admin_slot": "0x0b3296b6f50611B28d466a6D5A49754dAd4D8d9F"
  },
  "risk_flags": [],
  "asset_specific": {
    "type": "susdai",
    "decomposition": {
      "total_assets_usd": 300546332.06,
      "idle_usdai_usd": 52344083.78,
      "idle_pyusd_usd": 4040497.64,
      "deposit_timelock_escrow_usd": 140009710.21,
      "implied_deployed_loans_usd": 104152040.42,
      "api_loans_reserves_usd": 103075351.79,
      "recon_residual_pct": 0.010446,
      "credit_pipeline": {
        "drawn_usd": 104152040.42,
        "committed_undrawn_usd": 140009710.21,
        "total_loan_destined_usd": 244161750.63
      }
    },
    "nav_per_share": 1.088769,
    "discount_to_nav_pct": 0.3042,
    "asset_address": "0x0A1a1A107E45b7Ced86833863f482BC5f4ed82EF",
    "asset_matches_usdai": true,
    "secondary": {
      "source": "geckoterminal",
      "price_usd": 1.085457,
      "discount_to_nav_pct": 0.3042,
      "top_pools": [
        {
          "address": "0xe8c831687ce8c9d015eb10b430d1a54faa0cb4ed",
          "name": "sUSDai / USDT",
          "tvl_usd": 17625584.72,
          "vol_24h_usd": 407224.66
        },
        {
          "address": "0x86f874212335af27c41cdb855c2255543d1499ce",
          "name": "sUSDai / USDC",
          "tvl_usd": 16808949.3,
          "vol_24h_usd": 276738.26
        },
        {
          "address": "0xa7cf5543a27badc3a74d51ea0a02e84799140e4e",
          "name": "sUSDai / USDC",
          "tvl_usd": 1786761.29,
          "vol_24h_usd": 174325.77
        }
      ]
    },
    "slippage_tiers": {
      "susdai_to_usdc": {
        "1000": {
          "output_token": 998.99301,
          "output_usd": 998.99,
          "slippage_bps": 10.07,
          "gas_usd": "0.010569650730862733"
        },
        "10000": {
          "output_token": 9989.906295,
          "output_usd": 9989.91,
          "slippage_bps": 10.09,
          "gas_usd": "0.018125942212223592"
        },
        "100000": {
          "output_token": 99897.389962,
          "output_usd": 99897.39,
          "slippage_bps": 10.26,
          "gas_usd": "0.018128501547462227"
        },
        "500000": {
          "output_token": 499432.849155,
          "output_usd": 499432.85,
          "slippage_bps": 11.34,
          "gas_usd": "0.03994235034090668"
        }
      }
    }
  }
}