{
  "schema_version": 1,
  "asset": "sUSDai",
  "asset_slug": "susdai",
  "chain": "arbitrum",
  "timestamp": "2026-07-18T09:54:47Z",
  "as_of": "2026-07-18T09:54:47Z",
  "block_number": 485110139,
  "summary": {
    "total_assets_usd": 329288768.24,
    "share_supply": 179363491.41622,
    "nav_per_share": 1.098837,
    "buffer_ratio": 0.372455,
    "idle_usdai_usd": 122645269.22,
    "deposit_timelock_escrow_usd": 0.0,
    "implied_deployed_loans_usd": 204868299.23,
    "recon_residual_pct": 0.009963,
    "peg_secondary_px": 1.098299,
    "discount_to_nav_pct": 0.0489,
    "paused": false,
    "implementation": "0x23783eE86Db1a05DFc6DC2F042606a92c97A374C",
    "admin_slot": "0x0b3296b6f50611B28d466a6D5A49754dAd4D8d9F"
  },
  "risk_flags": [],
  "asset_specific": {
    "type": "susdai",
    "decomposition": {
      "total_assets_usd": 329288768.24,
      "idle_usdai_usd": 122645269.22,
      "idle_pyusd_usd": 1775199.79,
      "deposit_timelock_escrow_usd": 0.0,
      "implied_deployed_loans_usd": 204868299.23,
      "api_loans_reserves_usd": 202847427.82,
      "recon_residual_pct": 0.009963,
      "credit_pipeline": {
        "drawn_usd": 204868299.23,
        "committed_undrawn_usd": 0.0,
        "total_loan_destined_usd": 204868299.23
      }
    },
    "nav_per_share": 1.098837,
    "discount_to_nav_pct": 0.0489,
    "asset_address": "0x0A1a1A107E45b7Ced86833863f482BC5f4ed82EF",
    "asset_matches_usdai": true,
    "secondary": {
      "source": "geckoterminal",
      "price_usd": 1.098299,
      "discount_to_nav_pct": 0.0489,
      "top_pools": [
        {
          "address": "0x86f874212335af27c41cdb855c2255543d1499ce",
          "name": "sUSDai / USDC",
          "tvl_usd": 18075563.05,
          "vol_24h_usd": 1187322.64
        },
        {
          "address": "0xe8c831687ce8c9d015eb10b430d1a54faa0cb4ed",
          "name": "sUSDai / USDT",
          "tvl_usd": 17693463.33,
          "vol_24h_usd": 550166.59
        },
        {
          "address": "0xa7cf5543a27badc3a74d51ea0a02e84799140e4e",
          "name": "sUSDai / USDC",
          "tvl_usd": 1810142.66,
          "vol_24h_usd": 177396.91
        }
      ]
    },
    "slippage_tiers": {
      "susdai_to_usdc": {
        "1000": {
          "output_token": 999.298252,
          "output_usd": 999.3,
          "slippage_bps": 7.02,
          "gas_usd": "0.013047770211364097"
        },
        "10000": {
          "output_token": 9992.853432,
          "output_usd": 9992.85,
          "slippage_bps": 7.15,
          "gas_usd": "0.02619864491473419"
        },
        "100000": {
          "output_token": 99926.937515,
          "output_usd": 99926.94,
          "slippage_bps": 7.31,
          "gas_usd": "0.08380115919612643"
        },
        "500000": {
          "output_token": 499605.6448,
          "output_usd": 499605.64,
          "slippage_bps": 7.89,
          "gas_usd": "0.06388436303087935"
        }
      }
    }
  }
}