{
  "schema_version": 2,
  "asset": "USDD",
  "asset_slug": "usdd",
  "chain": "Tron + Ethereum + BNB Chain",
  "timestamp": "2026-04-23T10:39:17Z",
  "summary": {
    "total_supply": 1309089404.31,
    "total_backing": 1376966284.09,
    "collateral_ratio": 105.19,
    "collateral_ratio_alt": {
      "label": "Independent CR",
      "value": 35.72,
      "note": "User vaults only \u2014 excludes HTX-sourced collateral (SA + PSM)",
      "is_currency": false
    },
    "surplus_deficit": 67876879.78,
    "psm_coverage_pct": 13.9,
    "htx_pct": 66.0
  },
  "backing_breakdown": [
    {
      "label": "Smart Allocator (HTX)",
      "value": 727933499.0,
      "pct": 52.9,
      "tags": [
        "htx"
      ]
    },
    {
      "label": "PSM Reserves (HTX)",
      "value": 181406774.0,
      "pct": 13.2,
      "tags": [
        "htx"
      ]
    },
    {
      "label": "TRX Vaults (User)",
      "value": 456543991.0,
      "pct": 33.2,
      "tags": []
    },
    {
      "label": "sTRX Vaults (User)",
      "value": 10522341.0,
      "pct": 0.8,
      "tags": []
    },
    {
      "label": "USDT Vaults (User)",
      "value": 559678.0,
      "pct": 0.0,
      "tags": []
    }
  ],
  "risk_flags": [
    {
      "severity": "warning",
      "message": "Thin margin: Headline CR = 105.2%"
    },
    {
      "severity": "warning",
      "message": "HTX controls 66% of backing. Admin multisig can access funds (zero timelock)."
    },
    {
      "severity": "warning",
      "message": "Stress test: 50% TRX drop would push CR to 87.3% (below 100%)"
    }
  ],
  "asset_specific": {
    "type": "usdd",
    "supply_by_chain": {
      "tron": 1074361847.0,
      "ethereum": 124146228.0,
      "bsc": 110581329.0,
      "total": 1309089404.0
    },
    "psm_by_chain": {
      "tron": {
        "reserves_usd": 52696426.0,
        "chain_supply": 1074361847.0,
        "coverage_pct": 4.9
      },
      "ethereum": {
        "reserves_usd": 112266555.0,
        "chain_supply": 124146228.0,
        "coverage_pct": 90.4
      },
      "bsc": {
        "reserves_usd": 16443793.0,
        "chain_supply": 110581329.0,
        "coverage_pct": 14.9
      }
    },
    "psm_total_usd": 181406774.0,
    "psm_coverage_pct": 13.9,
    "collateral": {
      "smart_allocator": {
        "tron": 554698996.0,
        "ethereum": 173234503.0,
        "total": 727933499.0
      },
      "psm": {
        "tron": 52696426.0,
        "ethereum": 112266555.0,
        "bsc": 16443793.0,
        "total": 181406774.0
      },
      "trx_vaults_usd": 456543991.0,
      "strx_vaults_usd": 10522341.0,
      "usdt_vaults_usd": 559678.0,
      "other_vaults_usd": 0,
      "independent_total": 467626011.0,
      "htx_total": 909340273.0,
      "htx_pct": 66.0,
      "total": 1376966284.0
    },
    "ilks": {
      "tron:TRX-A": {
        "chain": "tron",
        "ilk": "TRX-A",
        "debt": 170345668.06,
        "ceiling": 400000000.0,
        "utilization_pct": 42.6,
        "is_htx": false
      },
      "tron:TRX-B": {
        "chain": "tron",
        "ilk": "TRX-B",
        "debt": 96010505.71,
        "ceiling": 300000000.0,
        "utilization_pct": 32.0,
        "is_htx": false
      },
      "tron:TRX-C": {
        "chain": "tron",
        "ilk": "TRX-C",
        "debt": 190187817.61,
        "ceiling": 400000000.0,
        "utilization_pct": 47.5,
        "is_htx": false
      },
      "tron:STRX-A": {
        "chain": "tron",
        "ilk": "STRX-A",
        "debt": 10522341.13,
        "ceiling": 200000000.0,
        "utilization_pct": 5.3,
        "is_htx": false
      },
      "tron:USDT-A": {
        "chain": "tron",
        "ilk": "USDT-A",
        "debt": 559678.32,
        "ceiling": 200000000.0,
        "utilization_pct": 0.3,
        "is_htx": false
      },
      "tron:PSM-USDT-A": {
        "chain": "tron",
        "ilk": "PSM-USDT-A",
        "debt": 52694907.28,
        "ceiling": 600000000.0,
        "utilization_pct": 8.8,
        "is_htx": true
      },
      "tron:SA001-A": {
        "chain": "tron",
        "ilk": "SA001-A",
        "debt": 554698996.0,
        "ceiling": 1000000000.0,
        "utilization_pct": 55.5,
        "is_htx": true
      },
      "ethereum:PSM-USDT-A": {
        "chain": "ethereum",
        "ilk": "PSM-USDT-A",
        "debt": 112266554.92,
        "ceiling": 500000000.0,
        "utilization_pct": 22.5,
        "is_htx": true
      },
      "ethereum:PSM-USDC-A": {
        "chain": "ethereum",
        "ilk": "PSM-USDC-A",
        "debt": 0.04,
        "ceiling": 10000000.0,
        "utilization_pct": 0.0,
        "is_htx": false
      },
      "ethereum:SA001-A": {
        "chain": "ethereum",
        "ilk": "SA001-A",
        "debt": 173234503.0,
        "ceiling": 620000000.0,
        "utilization_pct": 27.9,
        "is_htx": true
      },
      "bsc:PSM-USDT-A": {
        "chain": "bsc",
        "ilk": "PSM-USDT-A",
        "debt": 16443792.59,
        "ceiling": 200000000.0,
        "utilization_pct": 8.2,
        "is_htx": true
      }
    },
    "stress_test": {
      "trx_price": 0.3285,
      "trx_exposed_usd": 467066333.0,
      "stable_backing_usd": 909899952.0,
      "scenarios": {
        "trx_minus_30": {
          "drop_pct": 30,
          "trx_backing_usd": 326946433.0,
          "total_backing_usd": 1236846384.0,
          "cr_pct": 94.48
        },
        "trx_minus_50": {
          "drop_pct": 50,
          "trx_backing_usd": 233533166.0,
          "total_backing_usd": 1143433118.0,
          "cr_pct": 87.35
        },
        "trx_minus_70": {
          "drop_pct": 70,
          "trx_backing_usd": 140119900.0,
          "total_backing_usd": 1050019851.0,
          "cr_pct": 80.21
        }
      }
    },
    "peg": {
      "price": 1.0,
      "24h_change_pct": 0.003935868049535308,
      "market_cap": 1376970850.7208655,
      "volume_24h": 113820659.36117013
    },
    "trx_price": {
      "price": 0.3285,
      "24h_change_pct": -1.4348904179377606,
      "market_cap": 31135681302.773335,
      "volume_24h": 646203717.3452358
    },
    "htx_overlap": {
      "ethereum": {
        "htx_aave_usdt_total": 0,
        "htx_aave_usdt_addrs": [],
        "sa_aave_usdt": 0.0,
        "sa_protocol": "Spark",
        "htx_usdd_total": 0,
        "htx_usdd_addrs": []
      },
      "tron": {
        "htx_justlend_usdt_total": 17373747.0,
        "htx_justlend_usdt_addrs": [
          {
            "address": "TDToUxX8sH4z6moQpK3ZLAN24eupu2ivA4",
            "justlend_usdt": 17373747.0
          }
        ],
        "sa_justlend_usdt": 105199970.0,
        "htx_usdd_total": 17283314.0,
        "htx_usdd_addrs": [
          {
            "address": "TDToUxX8sH4z6moQpK3ZLAN24eupu2ivA4",
            "usdd": 11721485.0
          },
          {
            "address": "TK86Qm97uM848dMk8G7xNbJB7zG1uW3h1n",
            "usdd": 5362755.0
          },
          {
            "address": "TFTWNgDBkQ5wQoP8RXpRznnHvAVV8x5jLu",
            "usdd": 199074.0
          }
        ],
        "htx_vat_positions": []
      },
      "double_counted": false,
      "verdict": "No Aave double-counting: HTX deposits to Aave, SA deposits to Spark (different protocols). JustLend: 1 HTX addr(s) ($17.4M) + SA ($105.2M) \u2014 separate positions, same protocol. HTX addresses hold $17.3M USDD tokens across chains."
    },
    "htx_wallets": {
      "por_snapshot": {
        "date": "2026-03-01",
        "last_updated": "2026-03-09",
        "source": "github.com/huobiapi/Tool-Node.js-VerifyAddress/blob/main/snapshot/huobi_por.csv",
        "eth_addresses": 12,
        "tron_addresses": 15,
        "total_addresses": 27
      },
      "ethereum": {
        "addresses": [
          {
            "address": "0x18709E89BD403F470088aBDAcEbE86CC60dda12e",
            "usdt": 176799114.344383,
            "aave_usdt": 0.0,
            "eth": 663.0148174055302,
            "verification": "balance"
          },
          {
            "address": "0x4fb312915b779b1339388e14b6d079741ca83128",
            "usdt": 67902001.000125,
            "aave_usdt": 8.2e-05,
            "eth": 6621.100099987185,
            "verification": "balance"
          },
          {
            "address": "0x406ea8F3C6464171f3dEccF6Ba99748D9487CD52",
            "usdt": 0.0,
            "aave_usdt": 0.0,
            "eth": 0.2530485608615682,
            "verification": "signed"
          },
          {
            "address": "0xa03400e098f4421b34a3a44a1b4e571419517687",
            "usdt": 4404267.450061,
            "aave_usdt": 268.430731,
            "eth": 872.5169331868741,
            "verification": "balance"
          },
          {
            "address": "0x6663613fbd927ce78abbf7f5ca7e2c3fe0d96d18",
            "usdt": 0.0,
            "aave_usdt": 0.0,
            "eth": 1.0851906230519701,
            "verification": "balance"
          },
          {
            "address": "0x2a4bf9bbca7a91661087f52571eea36a004b83eb",
            "usdt": 1045412.186443,
            "aave_usdt": 0.0,
            "eth": 48.886115747280066,
            "verification": "balance"
          }
        ],
        "totals": {
          "usdt": 250150794.981012,
          "usdc": 0,
          "aave_usdt": 268.430813,
          "eth": 8206.85696311907
        }
      },
      "tron": {
        "addresses": [
          {
            "address": "TDToUxX8sH4z6moQpK3ZLAN24eupu2ivA4",
            "usdt": 0.0,
            "trx": 15318850.320679,
            "justlend_usdt": 17373746.53617621,
            "verification": "balance"
          },
          {
            "address": "TK86Qm97uM848dMk8G7xNbJB7zG1uW3h1n",
            "usdt": 86252999.312,
            "trx": 26292869.457952,
            "justlend_usdt": 0,
            "verification": "balance"
          },
          {
            "address": "TYh6mgoMNZTCsgpYHBz7gttEfrQmDMABub",
            "usdt": 22.953266,
            "trx": 122080527.160148,
            "justlend_usdt": 0,
            "verification": "balance"
          },
          {
            "address": "TGn1uvntAVntT1pG8o7qoKkbViiYfeg6Gj",
            "usdt": 13.002,
            "trx": 767110564.088379,
            "justlend_usdt": 0,
            "verification": "balance"
          },
          {
            "address": "TAuUCiH4JVNBZmDnEDZkXEUXDARdGpXTmX",
            "usdt": 0.003,
            "trx": 1434482068.204246,
            "justlend_usdt": 0,
            "verification": "balance"
          },
          {
            "address": "TF2fmSbg5HAD34KPUH7WtWCxxvgXHohzYM",
            "usdt": 0.012,
            "trx": 121266120.432543,
            "justlend_usdt": 0,
            "verification": "balance"
          },
          {
            "address": "THZovMcKoZaV9zzFTWteQYd2f3NEvnzxAM",
            "usdt": 0.011,
            "trx": 120385014.643045,
            "justlend_usdt": 0,
            "verification": "balance"
          },
          {
            "address": "TZ1SsapyhKNWaVLca6P2qgVzkHTdk6nkXa",
            "usdt": 0.004,
            "trx": 118083035.31877,
            "justlend_usdt": 0,
            "verification": "balance"
          },
          {
            "address": "TRSXRWudzfzY4jH7AaMowdMNUXDkHisbcd",
            "usdt": 0.023558,
            "trx": 629081775.076169,
            "justlend_usdt": 0,
            "verification": "balance"
          },
          {
            "address": "TCiRCBNFrL6bFKWL94yWQi5hNMGNp1Nu27",
            "usdt": 0.1,
            "trx": 6947.68203,
            "justlend_usdt": 0,
            "verification": "balance"
          },
          {
            "address": "TFTWNgDBkQ5wQoP8RXpRznnHvAVV8x5jLu",
            "usdt": 2671538.792798,
            "trx": 2649326.87591,
            "justlend_usdt": 0,
            "verification": "balance"
          },
          {
            "address": "TBuzWQynfzershAsPfGjo4A9sXUfZf8wsq",
            "usdt": 1909070.402545,
            "trx": 194.504108,
            "justlend_usdt": 0,
            "verification": "balance"
          }
        ],
        "totals": {
          "usdt": 90833644.61616701,
          "trx": 3356757420.4640255,
          "justlend_usdt": 17373746.53617621
        }
      },
      "grand_total_usd": 358358454.5641682
    },
    "htx_margin": {
      "por_snapshot_date": "2026-03-01",
      "por_user_usdt": 1319174371,
      "por_htx_usdt": 1320373524,
      "por_surplus": 1199153,
      "live_stablecoins": {
        "Tron:USDT": 91028202.0,
        "Tron:USDC": 0.0,
        "Tron:TUSD": 2498328.0,
        "Tron:STUSDT": 39010553.0,
        "Ethereum:USDT": 249013299.0,
        "Ethereum:USDC": 40492474.0,
        "Ethereum:TUSD": 2076225.0,
        "Ethereum:AETHUSDT": 268.0
      },
      "live_stablecoin_total": 424119349.0,
      "usdd_collateral_total": 909340273.0,
      "shortfall_ex_usdd": -895055022.0,
      "combined_surplus": 14285251.0,
      "defillama_available": true,
      "coverage_pct": 32.2
    },
    "psm_delta": {
      "current_usd": 181406774.0,
      "run_previous_usd": 185230460.0,
      "run_delta_usd": -3823686.0,
      "run_delta_pct": -2.06,
      "h24_previous_usd": null,
      "h24_delta_usd": null,
      "h24_delta_pct": null,
      "draining": false
    }
  }
}