{
  "schema_version": 1,
  "asset": "USG",
  "asset_slug": "usg",
  "chain": "Ethereum",
  "timestamp": "2026-07-10T05:38:02Z",
  "summary": {
    "real_supply": 2864487.86,
    "total_supply_raw": 42864298.27,
    "cdp_debt": 2864487.86,
    "pol_deployed": 0.0,
    "susg": 709649.16,
    "total_backing": 3509291.71,
    "total_collateral_value": 3509291.71,
    "pol_pool_stables": 1090993.52,
    "collateral_ratio": 122.51,
    "collateral_backed_share_pct": 122.51,
    "collateral_ratio_inclusive": 160.6,
    "pol_share_pct": 0.0,
    "max_oracle_overvaluation_pct": 0.1159,
    "max_nav_drift_pct": 0.4531,
    "n_oracle_divergent": 0,
    "worst_exotic_deviation_pct": -0.1396,
    "collateral_ratio_alt": {
      "label": "POL Pool Stables",
      "value": 1090993.52,
      "note": "USDC + frxUSD counter-side backing the POL-minted USG (PegKeeper pools). Excluded from the conservative CR; included in the inclusive CR.",
      "is_currency": true
    },
    "mint_cr": 122.5,
    "surplus_deficit": 1735797.38,
    "total_bad_debt": 0.0,
    "peg": 0.997817,
    "peg_deviation": -0.2183,
    "n_markets": 12,
    "n_active_markets": 12,
    "n_keepers": 2
  },
  "backing_breakdown": [
    {
      "label": "StakeDao Vault - frxUSD/sDOLA",
      "value": 620041.79,
      "pct": 17.7,
      "tags": [],
      "detail": {
        "debt": 501184.82,
        "collateral_value": 620041.79,
        "cr": 123.7,
        "maxLTV": 84.0,
        "liqThreshold": 85.25,
        "liqFee": 20.0,
        "badDebt": 0.0,
        "headroom_to_liq": 5.18,
        "oracle": "0x385B0c21d2f93a76468f8E074eDE3Ef6f8Ff13CE",
        "oracleName": "frxUSD_sDOLA/USD",
        "oracle_price": 1.016991,
        "oracle_price_optimistic": 1.016991,
        "oracle_spread_pct": 0.0,
        "virtual_price": 1.021134,
        "independent_nav": 1.02095,
        "nav_divergence_pct": -0.3877,
        "min_coin_symbol": "frxUSD",
        "min_coin_price": 0.99982,
        "pausedSettings": [
          0,
          0,
          0
        ],
        "market_type": "stakeDaoVault",
        "collateral_token": "0x9D8AFD5Ce19A3b948049468188f1De13951A4383",
        "collateral_qty": 609682.3798
      }
    },
    {
      "label": "Convex FXN - fxUSD/USDC",
      "value": 563971.84,
      "pct": 16.1,
      "tags": [
        "low-headroom"
      ],
      "detail": {
        "debt": 499867.32,
        "collateral_value": 563971.84,
        "cr": 112.8,
        "maxLTV": 90.0,
        "liqThreshold": 91.25,
        "liqFee": 20.0,
        "badDebt": 0.0,
        "headroom_to_liq": 2.87,
        "oracle": "0x35c62aC45DDF3079e2dAA0b8957862A1800920da",
        "oracleName": "USDC_fxUSD/USD",
        "oracle_price": 1.011869,
        "oracle_price_optimistic": 1.011869,
        "oracle_spread_pct": 0.0,
        "virtual_price": 1.012111,
        "independent_nav": 1.010697,
        "nav_divergence_pct": 0.1159,
        "min_coin_symbol": "fxUSD",
        "min_coin_price": 0.998604,
        "pausedSettings": [
          0,
          0,
          0
        ],
        "market_type": "convexFxn",
        "collateral_token": "0x5018BE882DccE5E3F2f3B0913AE2096B9b3fB61f",
        "collateral_qty": 557356.7453
      }
    },
    {
      "label": "Curve Gauge - RLUSD/USDC",
      "value": 485377.66,
      "pct": 13.8,
      "tags": [],
      "detail": {
        "debt": 410418.18,
        "collateral_value": 485377.66,
        "cr": 118.3,
        "maxLTV": 90.0,
        "liqThreshold": 91.5,
        "liqFee": 20.0,
        "badDebt": 0.0,
        "headroom_to_liq": 7.59,
        "oracle": "0xD0879E35783a165965d5cD524fC9b0D1cf02b066",
        "oracleName": "USDC_RLUSD/USD",
        "oracle_price": 1.009533,
        "oracle_price_optimistic": 1.009533,
        "oracle_spread_pct": 0.0,
        "virtual_price": 1.009774,
        "independent_nav": 1.009546,
        "nav_divergence_pct": -0.0013,
        "min_coin_symbol": "USDC",
        "min_coin_price": 0.999774,
        "pausedSettings": [
          0,
          0,
          0
        ],
        "market_type": "curveGauge",
        "collateral_token": "0xD001aE433f254283FeCE51d4ACcE8c53263aa186",
        "collateral_qty": 480794.2944
      }
    },
    {
      "label": "StakeDao Vault - BOLD/USDC",
      "value": 441926.63,
      "pct": 12.6,
      "tags": [],
      "detail": {
        "debt": 375034.8,
        "collateral_value": 441926.63,
        "cr": 117.8,
        "maxLTV": 90.0,
        "liqThreshold": 91.25,
        "liqFee": 20.0,
        "badDebt": 0.0,
        "headroom_to_liq": 7.0,
        "oracle": "0xf26B689dA847DB08F6bb3B3186FDF7eDdb8e69c9",
        "oracleName": "BOLD_USDC/USD",
        "oracle_price": 1.006731,
        "oracle_price_optimistic": 1.006731,
        "oracle_spread_pct": 0.0,
        "virtual_price": 1.006972,
        "independent_nav": 1.006744,
        "nav_divergence_pct": -0.0013,
        "min_coin_symbol": "USDC",
        "min_coin_price": 0.999774,
        "pausedSettings": [
          0,
          0,
          0
        ],
        "market_type": "stakeDaoVault",
        "collateral_token": "0xEFc6516323FbD28e80B85A497B65A86243a54B3E",
        "collateral_qty": 438971.9434
      }
    },
    {
      "label": "Curve Gauge - PYUSD/USDC",
      "value": 463771.68,
      "pct": 13.2,
      "tags": [],
      "detail": {
        "debt": 314158.69,
        "collateral_value": 463771.68,
        "cr": 147.6,
        "maxLTV": 90.0,
        "liqThreshold": 91.5,
        "liqFee": 20.0,
        "badDebt": 0.0,
        "headroom_to_liq": 25.97,
        "oracle": "0xcf434527AEFbc808E3E3400aB489a0E25c4af4ca",
        "oracleName": "PYUSD_USDC/USD",
        "oracle_price": 1.009489,
        "oracle_price_optimistic": 1.009489,
        "oracle_spread_pct": 0.0,
        "virtual_price": 1.00973,
        "independent_nav": 1.009502,
        "nav_divergence_pct": -0.0013,
        "min_coin_symbol": "USDC",
        "min_coin_price": 0.999774,
        "pausedSettings": [
          0,
          0,
          0
        ],
        "market_type": "curveGauge",
        "collateral_token": "0x383E6b4437b59fff47B619CBA855CA29342A8559",
        "collateral_qty": 459412.4775
      }
    },
    {
      "label": "StakeDao Vault - reUSD/scrvUSD",
      "value": 239882.94,
      "pct": 6.8,
      "tags": [
        "low-headroom"
      ],
      "detail": {
        "debt": 199919.69,
        "collateral_value": 239882.94,
        "cr": 120.0,
        "maxLTV": 84.0,
        "liqThreshold": 85.0,
        "liqFee": 20.0,
        "badDebt": 0.0,
        "headroom_to_liq": 1.95,
        "oracle": "0xdB0fc4aE74FA8D8a1C3d31e6e9113DBc8B2c7DAA",
        "oracleName": "reUSD_scrvUSD/USD",
        "oracle_price": 1.016971,
        "oracle_price_optimistic": 1.016971,
        "oracle_spread_pct": 0.0,
        "virtual_price": 1.022571,
        "independent_nav": 1.021601,
        "nav_divergence_pct": -0.4531,
        "min_coin_symbol": "reUSD",
        "min_coin_price": 0.999051,
        "pausedSettings": [
          0,
          0,
          0
        ],
        "market_type": "stakeDaoVault",
        "collateral_token": "0xc522A6606BBA746d7960404F22a3DB936B6F4F50",
        "collateral_qty": 235879.7387
      }
    },
    {
      "label": "Convex FXN - reUSD/fxUSD",
      "value": 239576.24,
      "pct": 6.8,
      "tags": [
        "low-headroom"
      ],
      "detail": {
        "debt": 199748.7,
        "collateral_value": 239576.24,
        "cr": 119.9,
        "maxLTV": 84.0,
        "liqThreshold": 85.0,
        "liqFee": 20.0,
        "badDebt": 0.0,
        "headroom_to_liq": 1.91,
        "oracle": "0x9f162292Bc39F194a3CA87e39700293bD9aa710A",
        "oracleName": "reUSD_fxUSD/USD",
        "oracle_price": 0.998828,
        "oracle_price_optimistic": 0.998828,
        "oracle_spread_pct": 0.0,
        "virtual_price": 1.004327,
        "independent_nav": 1.002925,
        "nav_divergence_pct": -0.4085,
        "min_coin_symbol": "fxUSD",
        "min_coin_price": 0.998604,
        "pausedSettings": [
          0,
          0,
          0
        ],
        "market_type": "convexFxn",
        "collateral_token": "0xb0ef04ACE97d350E24Efa5139d2590D26a61A8Dc",
        "collateral_qty": 239857.4626
      }
    },
    {
      "label": "StakeDao Vault - frxUSD/sUSDS",
      "value": 255444.9,
      "pct": 7.3,
      "tags": [],
      "detail": {
        "debt": 199441.81,
        "collateral_value": 255444.9,
        "cr": 128.1,
        "maxLTV": 90.0,
        "liqThreshold": 91.25,
        "liqFee": 20.0,
        "badDebt": 0.0,
        "headroom_to_liq": 14.44,
        "oracle": "0x3ccd01E66172b2c1B3C17f485B7F2987Ae94dA6A",
        "oracleName": "frxUSD_sUSDS/USD",
        "oracle_price": 1.038407,
        "oracle_price_optimistic": 1.038407,
        "oracle_spread_pct": 0.0,
        "virtual_price": 1.038806,
        "independent_nav": 1.038619,
        "nav_divergence_pct": -0.0204,
        "min_coin_symbol": "frxUSD",
        "min_coin_price": 0.99982,
        "pausedSettings": [
          0,
          0,
          0
        ],
        "market_type": "stakeDaoVault",
        "collateral_token": "0x81A2612F6dEA269a6Dd1F6DeAb45C5424EE2c4b7",
        "collateral_qty": 245996.8404
      }
    },
    {
      "label": "StakeDao Vault - frxUSD/OUSD",
      "value": 84438.49,
      "pct": 2.4,
      "tags": [],
      "detail": {
        "debt": 72627.09,
        "collateral_value": 84438.49,
        "cr": 116.3,
        "maxLTV": 87.5,
        "liqThreshold": 88.75,
        "liqFee": 20.0,
        "badDebt": 0.0,
        "headroom_to_liq": 3.09,
        "oracle": "0xe3e9628d2B047Aa43Ab08Adc1B5Bb059ca0b1268",
        "oracleName": "frxUSD_OUSD/USD",
        "oracle_price": 1.00024,
        "oracle_price_optimistic": 1.00024,
        "oracle_spread_pct": 0.0,
        "virtual_price": 1.000852,
        "independent_nav": 1.00012,
        "nav_divergence_pct": 0.012,
        "min_coin_symbol": "OUSD",
        "min_coin_price": 0.999268,
        "pausedSettings": [
          0,
          0,
          0
        ],
        "market_type": "stakeDaoVault",
        "collateral_token": "0x68d03Ed49800e92D7Aa8aB171424007e55Fd1F49",
        "collateral_qty": 84418.263
      }
    },
    {
      "label": "StakeDao Vault - USDT/crvUSD",
      "value": 76967.68,
      "pct": 2.2,
      "tags": [],
      "detail": {
        "debt": 61947.8,
        "collateral_value": 76967.68,
        "cr": 124.2,
        "maxLTV": 84.0,
        "liqThreshold": 85.25,
        "liqFee": 20.0,
        "badDebt": 0.0,
        "headroom_to_liq": 5.59,
        "oracle": "0x5d34f650c779124676Cd72922112A997A4173AEF",
        "oracleName": "USDT_crvUSD/USD",
        "oracle_price": 1.025921,
        "oracle_price_optimistic": 1.025921,
        "oracle_spread_pct": 0.0,
        "virtual_price": 1.026797,
        "independent_nav": 1.025971,
        "nav_divergence_pct": -0.0049,
        "min_coin_symbol": "USDT",
        "min_coin_price": 0.999196,
        "pausedSettings": [
          0,
          0,
          0
        ],
        "market_type": "stakeDaoVault",
        "collateral_token": "0x390f3595bCa2Df7d23783dFd126427CCeb997BF4",
        "collateral_qty": 75023.0003
      }
    },
    {
      "label": "StakeDao Vault - frxUSD/scrvUSD",
      "value": 33217.3,
      "pct": 0.9,
      "tags": [],
      "detail": {
        "debt": 26622.98,
        "collateral_value": 33217.3,
        "cr": 124.8,
        "maxLTV": 84.0,
        "liqThreshold": 85.25,
        "liqFee": 20.0,
        "badDebt": 0.0,
        "headroom_to_liq": 5.98,
        "oracle": "0xF31BE70c9D9596B23088125345F044065b0Bf886",
        "oracleName": "frxUSD_scrvUSD/USD",
        "oracle_price": 1.040028,
        "oracle_price_optimistic": 1.040028,
        "oracle_spread_pct": 0.0,
        "virtual_price": 1.040889,
        "independent_nav": 1.040701,
        "nav_divergence_pct": -0.0647,
        "min_coin_symbol": "frxUSD",
        "min_coin_price": 0.99982,
        "pausedSettings": [
          0,
          0,
          0
        ],
        "market_type": "stakeDaoVault",
        "collateral_token": "0x4d968a5Db8dA0822A2F08840f553De4129aAe5F3",
        "collateral_qty": 31938.8479
      }
    },
    {
      "label": "StakeDao Vault - eUSD/USDC",
      "value": 4674.57,
      "pct": 0.1,
      "tags": [],
      "detail": {
        "debt": 3515.97,
        "collateral_value": 4674.57,
        "cr": 133.0,
        "maxLTV": 87.5,
        "liqThreshold": 88.75,
        "liqFee": 20.0,
        "badDebt": 0.0,
        "headroom_to_liq": 15.25,
        "oracle": "0xb8Cc9E84941605F553004d188e31e2aeB4061fD2",
        "oracleName": "eUSD_USDC/USD",
        "oracle_price": 1.014875,
        "oracle_price_optimistic": 1.014875,
        "oracle_spread_pct": 0.0,
        "virtual_price": 1.01571,
        "independent_nav": 1.015263,
        "nav_divergence_pct": -0.0382,
        "min_coin_symbol": "eUSD",
        "min_coin_price": 0.99956,
        "pausedSettings": [
          0,
          0,
          0
        ],
        "market_type": "stakeDaoVault",
        "collateral_token": "0x08BfA22bB3e024CDfEB3eca53c0cb93bF59c4147",
        "collateral_qty": 4606.0597
      }
    }
  ],
  "risk_flags": [
    {
      "key": "usg_ok",
      "severity": "info",
      "message": "No critical risk flags"
    }
  ],
  "vault_status": null,
  "asset_specific": {
    "type": "usg",
    "markets": [
      {
        "name": "StakeDao Vault - frxUSD/sDOLA",
        "market": "0xd3d29a8752fc40d64a20bbc043147077570c1785",
        "market_type": "stakeDaoVault",
        "collateral_token": "0x9D8AFD5Ce19A3b948049468188f1De13951A4383",
        "oracle": "0x385B0c21d2f93a76468f8E074eDE3Ef6f8Ff13CE",
        "oracle_name": "frxUSD_sDOLA/USD",
        "debt": 501184.82,
        "collateral_qty": 609682.3798,
        "oracle_price": 1.016991,
        "oracle_price_optimistic": 1.016991,
        "oracle_spread_pct": 0.0,
        "virtual_price": 1.021134,
        "independent_nav": 1.02095,
        "nav_divergence_pct": -0.3877,
        "min_coin_symbol": "frxUSD",
        "min_coin_price": 0.99982,
        "pool_coins": [
          "0xCAcd6fd266aF91b8AeD52aCCc382b4e165586E29",
          "0xb45ad160634c528Cc3D2926d9807104FA3157305"
        ],
        "pool_coin_prices": [
          {
            "address": "0xCAcd6fd266aF91b8AeD52aCCc382b4e165586E29",
            "symbol": "frxUSD",
            "price": 0.9998198396150635
          },
          {
            "address": "0xb45ad160634c528Cc3D2926d9807104FA3157305",
            "symbol": "sDOLA",
            "price": 1.3914249543858384
          }
        ],
        "collateral_value": 620041.79,
        "cr": 123.7,
        "maxLTV": 84.0,
        "liqThreshold": 85.25,
        "liqFee": 20.0,
        "badDebt": 0.0,
        "headroom_to_liq": 5.18,
        "pausedSettings": [
          0,
          0,
          0
        ]
      },
      {
        "name": "Convex FXN - fxUSD/USDC",
        "market": "0x849cf82e0ebcfeab8270cc5a3ea3b26cd481b754",
        "market_type": "convexFxn",
        "collateral_token": "0x5018BE882DccE5E3F2f3B0913AE2096B9b3fB61f",
        "oracle": "0x35c62aC45DDF3079e2dAA0b8957862A1800920da",
        "oracle_name": "USDC_fxUSD/USD",
        "debt": 499867.32,
        "collateral_qty": 557356.7453,
        "oracle_price": 1.011869,
        "oracle_price_optimistic": 1.011869,
        "oracle_spread_pct": 0.0,
        "virtual_price": 1.012111,
        "independent_nav": 1.010697,
        "nav_divergence_pct": 0.1159,
        "min_coin_symbol": "fxUSD",
        "min_coin_price": 0.998604,
        "pool_coins": [
          "0xA0b86991c6218b36c1d19D4a2e9Eb0cE3606eB48",
          "0x085780639CC2cACd35E474e71f4d000e2405d8f6"
        ],
        "pool_coin_prices": [
          {
            "address": "0xA0b86991c6218b36c1d19D4a2e9Eb0cE3606eB48",
            "symbol": "USDC",
            "price": 0.9997739674448525
          },
          {
            "address": "0x085780639CC2cACd35E474e71f4d000e2405d8f6",
            "symbol": "fxUSD",
            "price": 0.9986036667795735
          }
        ],
        "collateral_value": 563971.84,
        "cr": 112.8,
        "maxLTV": 90.0,
        "liqThreshold": 91.25,
        "liqFee": 20.0,
        "badDebt": 0.0,
        "headroom_to_liq": 2.87,
        "pausedSettings": [
          0,
          0,
          0
        ]
      },
      {
        "name": "Curve Gauge - RLUSD/USDC",
        "market": "0xbffbd9c9ac1645285d017a69885304831e8b9b71",
        "market_type": "curveGauge",
        "collateral_token": "0xD001aE433f254283FeCE51d4ACcE8c53263aa186",
        "oracle": "0xD0879E35783a165965d5cD524fC9b0D1cf02b066",
        "oracle_name": "USDC_RLUSD/USD",
        "debt": 410418.18,
        "collateral_qty": 480794.2944,
        "oracle_price": 1.009533,
        "oracle_price_optimistic": 1.009533,
        "oracle_spread_pct": 0.0,
        "virtual_price": 1.009774,
        "independent_nav": 1.009546,
        "nav_divergence_pct": -0.0013,
        "min_coin_symbol": "USDC",
        "min_coin_price": 0.999774,
        "pool_coins": [
          "0xA0b86991c6218b36c1d19D4a2e9Eb0cE3606eB48",
          "0x8292Bb45bf1Ee4d140127049757C2E0fF06317eD"
        ],
        "pool_coin_prices": [
          {
            "address": "0xA0b86991c6218b36c1d19D4a2e9Eb0cE3606eB48",
            "symbol": "USDC",
            "price": 0.9997739674448525
          },
          {
            "address": "0x8292Bb45bf1Ee4d140127049757C2E0fF06317eD",
            "symbol": "RLUSD",
            "price": 1.0000228079871893
          }
        ],
        "collateral_value": 485377.66,
        "cr": 118.3,
        "maxLTV": 90.0,
        "liqThreshold": 91.5,
        "liqFee": 20.0,
        "badDebt": 0.0,
        "headroom_to_liq": 7.59,
        "pausedSettings": [
          0,
          0,
          0
        ]
      },
      {
        "name": "StakeDao Vault - BOLD/USDC",
        "market": "0xc9c80e8481c2b6f979afc155bc3f979cfad19c56",
        "market_type": "stakeDaoVault",
        "collateral_token": "0xEFc6516323FbD28e80B85A497B65A86243a54B3E",
        "oracle": "0xf26B689dA847DB08F6bb3B3186FDF7eDdb8e69c9",
        "oracle_name": "BOLD_USDC/USD",
        "debt": 375034.8,
        "collateral_qty": 438971.9434,
        "oracle_price": 1.006731,
        "oracle_price_optimistic": 1.006731,
        "oracle_spread_pct": 0.0,
        "virtual_price": 1.006972,
        "independent_nav": 1.006744,
        "nav_divergence_pct": -0.0013,
        "min_coin_symbol": "USDC",
        "min_coin_price": 0.999774,
        "pool_coins": [
          "0x6440f144b7e50D6a8439336510312d2F54beB01D",
          "0xA0b86991c6218b36c1d19D4a2e9Eb0cE3606eB48"
        ],
        "pool_coin_prices": [
          {
            "address": "0x6440f144b7e50D6a8439336510312d2F54beB01D",
            "symbol": "BOLD",
            "price": 1.0011216596959367
          },
          {
            "address": "0xA0b86991c6218b36c1d19D4a2e9Eb0cE3606eB48",
            "symbol": "USDC",
            "price": 0.9997739674448525
          }
        ],
        "collateral_value": 441926.63,
        "cr": 117.8,
        "maxLTV": 90.0,
        "liqThreshold": 91.25,
        "liqFee": 20.0,
        "badDebt": 0.0,
        "headroom_to_liq": 7.0,
        "pausedSettings": [
          0,
          0,
          0
        ]
      },
      {
        "name": "Curve Gauge - PYUSD/USDC",
        "market": "0x4742a56668fbacbc11087f516c4b01ebc48f716f",
        "market_type": "curveGauge",
        "collateral_token": "0x383E6b4437b59fff47B619CBA855CA29342A8559",
        "oracle": "0xcf434527AEFbc808E3E3400aB489a0E25c4af4ca",
        "oracle_name": "PYUSD_USDC/USD",
        "debt": 314158.69,
        "collateral_qty": 459412.4775,
        "oracle_price": 1.009489,
        "oracle_price_optimistic": 1.009489,
        "oracle_spread_pct": 0.0,
        "virtual_price": 1.00973,
        "independent_nav": 1.009502,
        "nav_divergence_pct": -0.0013,
        "min_coin_symbol": "USDC",
        "min_coin_price": 0.999774,
        "pool_coins": [
          "0x6c3ea9036406852006290770BEdFcAbA0e23A0e8",
          "0xA0b86991c6218b36c1d19D4a2e9Eb0cE3606eB48"
        ],
        "pool_coin_prices": [
          {
            "address": "0x6c3ea9036406852006290770BEdFcAbA0e23A0e8",
            "symbol": "PYUSD",
            "price": 0.9999013954511249
          },
          {
            "address": "0xA0b86991c6218b36c1d19D4a2e9Eb0cE3606eB48",
            "symbol": "USDC",
            "price": 0.9997739674448525
          }
        ],
        "collateral_value": 463771.68,
        "cr": 147.6,
        "maxLTV": 90.0,
        "liqThreshold": 91.5,
        "liqFee": 20.0,
        "badDebt": 0.0,
        "headroom_to_liq": 25.97,
        "pausedSettings": [
          0,
          0,
          0
        ]
      },
      {
        "name": "StakeDao Vault - reUSD/scrvUSD",
        "market": "0x161d6fa48b0e0152763c3929a3813bd177fc099f",
        "market_type": "stakeDaoVault",
        "collateral_token": "0xc522A6606BBA746d7960404F22a3DB936B6F4F50",
        "oracle": "0xdB0fc4aE74FA8D8a1C3d31e6e9113DBc8B2c7DAA",
        "oracle_name": "reUSD_scrvUSD/USD",
        "debt": 199919.69,
        "collateral_qty": 235879.7387,
        "oracle_price": 1.016971,
        "oracle_price_optimistic": 1.016971,
        "oracle_spread_pct": 0.0,
        "virtual_price": 1.022571,
        "independent_nav": 1.021601,
        "nav_divergence_pct": -0.4531,
        "min_coin_symbol": "reUSD",
        "min_coin_price": 0.999051,
        "pool_coins": [
          "0x57aB1E0003F623289CD798B1824Be09a793e4Bec",
          "0x0655977FEb2f289A4aB78af67BAB0d17aAb84367"
        ],
        "pool_coin_prices": [
          {
            "address": "0x57aB1E0003F623289CD798B1824Be09a793e4Bec",
            "symbol": "reUSD",
            "price": 0.9990511480988025
          },
          {
            "address": "0x0655977FEb2f289A4aB78af67BAB0d17aAb84367",
            "symbol": "scrvUSD",
            "price": 1.1042159884784797
          }
        ],
        "collateral_value": 239882.94,
        "cr": 120.0,
        "maxLTV": 84.0,
        "liqThreshold": 85.0,
        "liqFee": 20.0,
        "badDebt": 0.0,
        "headroom_to_liq": 1.95,
        "pausedSettings": [
          0,
          0,
          0
        ]
      },
      {
        "name": "Convex FXN - reUSD/fxUSD",
        "market": "0xa63ded87df22ee573567ad1dd87d0a71c8fcd380",
        "market_type": "convexFxn",
        "collateral_token": "0xb0ef04ACE97d350E24Efa5139d2590D26a61A8Dc",
        "oracle": "0x9f162292Bc39F194a3CA87e39700293bD9aa710A",
        "oracle_name": "reUSD_fxUSD/USD",
        "debt": 199748.7,
        "collateral_qty": 239857.4626,
        "oracle_price": 0.998828,
        "oracle_price_optimistic": 0.998828,
        "oracle_spread_pct": 0.0,
        "virtual_price": 1.004327,
        "independent_nav": 1.002925,
        "nav_divergence_pct": -0.4085,
        "min_coin_symbol": "fxUSD",
        "min_coin_price": 0.998604,
        "pool_coins": [
          "0x57aB1E0003F623289CD798B1824Be09a793e4Bec",
          "0x085780639CC2cACd35E474e71f4d000e2405d8f6"
        ],
        "pool_coin_prices": [
          {
            "address": "0x57aB1E0003F623289CD798B1824Be09a793e4Bec",
            "symbol": "reUSD",
            "price": 0.9990511480988025
          },
          {
            "address": "0x085780639CC2cACd35E474e71f4d000e2405d8f6",
            "symbol": "fxUSD",
            "price": 0.9986036667795735
          }
        ],
        "collateral_value": 239576.24,
        "cr": 119.9,
        "maxLTV": 84.0,
        "liqThreshold": 85.0,
        "liqFee": 20.0,
        "badDebt": 0.0,
        "headroom_to_liq": 1.91,
        "pausedSettings": [
          0,
          0,
          0
        ]
      },
      {
        "name": "StakeDao Vault - frxUSD/sUSDS",
        "market": "0xd2c7257efe28a1b1446904a371e3d51e1c2f7e0e",
        "market_type": "stakeDaoVault",
        "collateral_token": "0x81A2612F6dEA269a6Dd1F6DeAb45C5424EE2c4b7",
        "oracle": "0x3ccd01E66172b2c1B3C17f485B7F2987Ae94dA6A",
        "oracle_name": "frxUSD_sUSDS/USD",
        "debt": 199441.81,
        "collateral_qty": 245996.8404,
        "oracle_price": 1.038407,
        "oracle_price_optimistic": 1.038407,
        "oracle_spread_pct": 0.0,
        "virtual_price": 1.038806,
        "independent_nav": 1.038619,
        "nav_divergence_pct": -0.0204,
        "min_coin_symbol": "frxUSD",
        "min_coin_price": 0.99982,
        "pool_coins": [
          "0xCAcd6fd266aF91b8AeD52aCCc382b4e165586E29",
          "0xa3931d71877C0E7a3148CB7Eb4463524FEc27fbD"
        ],
        "pool_coin_prices": [
          {
            "address": "0xCAcd6fd266aF91b8AeD52aCCc382b4e165586E29",
            "symbol": "frxUSD",
            "price": 0.9998198396150635
          },
          {
            "address": "0xa3931d71877C0E7a3148CB7Eb4463524FEc27fbD",
            "symbol": "sUSDS",
            "price": 1.1021696565239063
          }
        ],
        "collateral_value": 255444.9,
        "cr": 128.1,
        "maxLTV": 90.0,
        "liqThreshold": 91.25,
        "liqFee": 20.0,
        "badDebt": 0.0,
        "headroom_to_liq": 14.44,
        "pausedSettings": [
          0,
          0,
          0
        ]
      },
      {
        "name": "StakeDao Vault - frxUSD/OUSD",
        "market": "0x56dbc69208044748af4d33392e25fc9336f11931",
        "market_type": "stakeDaoVault",
        "collateral_token": "0x68d03Ed49800e92D7Aa8aB171424007e55Fd1F49",
        "oracle": "0xe3e9628d2B047Aa43Ab08Adc1B5Bb059ca0b1268",
        "oracle_name": "frxUSD_OUSD/USD",
        "debt": 72627.09,
        "collateral_qty": 84418.263,
        "oracle_price": 1.00024,
        "oracle_price_optimistic": 1.00024,
        "oracle_spread_pct": 0.0,
        "virtual_price": 1.000852,
        "independent_nav": 1.00012,
        "nav_divergence_pct": 0.012,
        "min_coin_symbol": "OUSD",
        "min_coin_price": 0.999268,
        "pool_coins": [
          "0xCAcd6fd266aF91b8AeD52aCCc382b4e165586E29",
          "0x2A8e1E676Ec238d8A992307B495b45B3fEAa5e86"
        ],
        "pool_coin_prices": [
          {
            "address": "0xCAcd6fd266aF91b8AeD52aCCc382b4e165586E29",
            "symbol": "frxUSD",
            "price": 0.9998198396150635
          },
          {
            "address": "0x2A8e1E676Ec238d8A992307B495b45B3fEAa5e86",
            "symbol": "OUSD",
            "price": 0.9992684024386816
          }
        ],
        "collateral_value": 84438.49,
        "cr": 116.3,
        "maxLTV": 87.5,
        "liqThreshold": 88.75,
        "liqFee": 20.0,
        "badDebt": 0.0,
        "headroom_to_liq": 3.09,
        "pausedSettings": [
          0,
          0,
          0
        ]
      },
      {
        "name": "StakeDao Vault - USDT/crvUSD",
        "market": "0xaed9bcae0831caf4a45739ec7910cedf2ac5d9a1",
        "market_type": "stakeDaoVault",
        "collateral_token": "0x390f3595bCa2Df7d23783dFd126427CCeb997BF4",
        "oracle": "0x5d34f650c779124676Cd72922112A997A4173AEF",
        "oracle_name": "USDT_crvUSD/USD",
        "debt": 61947.8,
        "collateral_qty": 75023.0003,
        "oracle_price": 1.025921,
        "oracle_price_optimistic": 1.025921,
        "oracle_spread_pct": 0.0,
        "virtual_price": 1.026797,
        "independent_nav": 1.025971,
        "nav_divergence_pct": -0.0049,
        "min_coin_symbol": "USDT",
        "min_coin_price": 0.999196,
        "pool_coins": [
          "0xdAC17F958D2ee523a2206206994597C13D831ec7",
          "0xf939E0A03FB07F59A73314E73794Be0E57ac1b4E"
        ],
        "pool_coin_prices": [
          {
            "address": "0xdAC17F958D2ee523a2206206994597C13D831ec7",
            "symbol": "USDT",
            "price": 0.9991958038512329
          },
          {
            "address": "0xf939E0A03FB07F59A73314E73794Be0E57ac1b4E",
            "symbol": "crvUSD",
            "price": 0.9993599422395381
          }
        ],
        "collateral_value": 76967.68,
        "cr": 124.2,
        "maxLTV": 84.0,
        "liqThreshold": 85.25,
        "liqFee": 20.0,
        "badDebt": 0.0,
        "headroom_to_liq": 5.59,
        "pausedSettings": [
          0,
          0,
          0
        ]
      },
      {
        "name": "StakeDao Vault - frxUSD/scrvUSD",
        "market": "0x5c996574270f439bfff5b7647ee92c1879d35a4b",
        "market_type": "stakeDaoVault",
        "collateral_token": "0x4d968a5Db8dA0822A2F08840f553De4129aAe5F3",
        "oracle": "0xF31BE70c9D9596B23088125345F044065b0Bf886",
        "oracle_name": "frxUSD_scrvUSD/USD",
        "debt": 26622.98,
        "collateral_qty": 31938.8479,
        "oracle_price": 1.040028,
        "oracle_price_optimistic": 1.040028,
        "oracle_spread_pct": 0.0,
        "virtual_price": 1.040889,
        "independent_nav": 1.040701,
        "nav_divergence_pct": -0.0647,
        "min_coin_symbol": "frxUSD",
        "min_coin_price": 0.99982,
        "pool_coins": [
          "0xCAcd6fd266aF91b8AeD52aCCc382b4e165586E29",
          "0x0655977FEb2f289A4aB78af67BAB0d17aAb84367"
        ],
        "pool_coin_prices": [
          {
            "address": "0xCAcd6fd266aF91b8AeD52aCCc382b4e165586E29",
            "symbol": "frxUSD",
            "price": 0.9998198396150635
          },
          {
            "address": "0x0655977FEb2f289A4aB78af67BAB0d17aAb84367",
            "symbol": "scrvUSD",
            "price": 1.1042159884784797
          }
        ],
        "collateral_value": 33217.3,
        "cr": 124.8,
        "maxLTV": 84.0,
        "liqThreshold": 85.25,
        "liqFee": 20.0,
        "badDebt": 0.0,
        "headroom_to_liq": 5.98,
        "pausedSettings": [
          0,
          0,
          0
        ]
      },
      {
        "name": "StakeDao Vault - eUSD/USDC",
        "market": "0xa6069a4a53b564eb0a312e08f5af19ae2ba5d67e",
        "market_type": "stakeDaoVault",
        "collateral_token": "0x08BfA22bB3e024CDfEB3eca53c0cb93bF59c4147",
        "oracle": "0xb8Cc9E84941605F553004d188e31e2aeB4061fD2",
        "oracle_name": "eUSD_USDC/USD",
        "debt": 3515.97,
        "collateral_qty": 4606.0597,
        "oracle_price": 1.014875,
        "oracle_price_optimistic": 1.014875,
        "oracle_spread_pct": 0.0,
        "virtual_price": 1.01571,
        "independent_nav": 1.015263,
        "nav_divergence_pct": -0.0382,
        "min_coin_symbol": "eUSD",
        "min_coin_price": 0.99956,
        "pool_coins": [
          "0xA0d69E286B938e21CBf7E51D71F6A4c8918f482F",
          "0xA0b86991c6218b36c1d19D4a2e9Eb0cE3606eB48"
        ],
        "pool_coin_prices": [
          {
            "address": "0xA0d69E286B938e21CBf7E51D71F6A4c8918f482F",
            "symbol": "eUSD",
            "price": 0.9995596799048392
          },
          {
            "address": "0xA0b86991c6218b36c1d19D4a2e9Eb0cE3606eB48",
            "symbol": "USDC",
            "price": 0.9997739674448525
          }
        ],
        "collateral_value": 4674.57,
        "cr": 133.0,
        "maxLTV": 87.5,
        "liqThreshold": 88.75,
        "liqFee": 20.0,
        "badDebt": 0.0,
        "headroom_to_liq": 15.25,
        "pausedSettings": [
          0,
          0,
          0
        ]
      }
    ],
    "exotic_pegs": [
      {
        "symbol": "fxUSD",
        "address": "0x085780639CC2cACd35E474e71f4d000e2405d8f6",
        "price": 0.998604,
        "aggregator_price": 0.998604,
        "executable_price": 0.999932,
        "divergence_bps": -13,
        "price_artifact": false,
        "deviation_pct": -0.1396,
        "par_target": true,
        "in_markets": [
          "Convex FXN - fxUSD/USDC",
          "Convex FXN - reUSD/fxUSD"
        ]
      },
      {
        "symbol": "reUSD",
        "address": "0x57aB1E0003F623289CD798B1824Be09a793e4Bec",
        "price": 0.999051,
        "aggregator_price": 0.999051,
        "executable_price": 0.994721,
        "divergence_bps": 44,
        "price_artifact": false,
        "deviation_pct": -0.0949,
        "par_target": true,
        "in_markets": [
          "Convex FXN - reUSD/fxUSD",
          "StakeDao Vault - reUSD/scrvUSD"
        ]
      },
      {
        "symbol": "OUSD",
        "address": "0x2A8e1E676Ec238d8A992307B495b45B3fEAa5e86",
        "price": 0.999268,
        "aggregator_price": 0.999268,
        "executable_price": 0.99952,
        "divergence_bps": -3,
        "price_artifact": false,
        "deviation_pct": -0.0732,
        "par_target": true,
        "in_markets": [
          "StakeDao Vault - frxUSD/OUSD"
        ]
      },
      {
        "symbol": "crvUSD",
        "address": "0xf939E0A03FB07F59A73314E73794Be0E57ac1b4E",
        "price": 0.99936,
        "aggregator_price": 0.99936,
        "executable_price": 0.999955,
        "divergence_bps": -6,
        "price_artifact": false,
        "deviation_pct": -0.064,
        "par_target": true,
        "in_markets": [
          "StakeDao Vault - USDT/crvUSD"
        ]
      },
      {
        "symbol": "eUSD",
        "address": "0xA0d69E286B938e21CBf7E51D71F6A4c8918f482F",
        "price": 0.99956,
        "aggregator_price": 0.99956,
        "executable_price": 0.999262,
        "divergence_bps": 3,
        "price_artifact": false,
        "deviation_pct": -0.044,
        "par_target": true,
        "in_markets": [
          "StakeDao Vault - eUSD/USDC"
        ]
      },
      {
        "symbol": "BOLD",
        "address": "0x6440f144b7e50D6a8439336510312d2F54beB01D",
        "price": 1.001122,
        "aggregator_price": 1.001122,
        "executable_price": 1.00139,
        "divergence_bps": -3,
        "price_artifact": false,
        "deviation_pct": 0.1122,
        "par_target": true,
        "in_markets": [
          "StakeDao Vault - BOLD/USDC"
        ]
      },
      {
        "symbol": "sDOLA",
        "address": "0xb45ad160634c528Cc3D2926d9807104FA3157305",
        "price": 1.391425,
        "aggregator_price": 1.391425,
        "executable_price": null,
        "divergence_bps": null,
        "price_artifact": false,
        "deviation_pct": null,
        "par_target": false,
        "in_markets": [
          "StakeDao Vault - frxUSD/sDOLA"
        ]
      },
      {
        "symbol": "scrvUSD",
        "address": "0x0655977FEb2f289A4aB78af67BAB0d17aAb84367",
        "price": 1.104216,
        "aggregator_price": 1.104216,
        "executable_price": null,
        "divergence_bps": null,
        "price_artifact": false,
        "deviation_pct": null,
        "par_target": false,
        "in_markets": [
          "StakeDao Vault - frxUSD/scrvUSD",
          "StakeDao Vault - reUSD/scrvUSD"
        ]
      }
    ],
    "oracle_nav": {
      "max_overvaluation_pct": 0.1159,
      "max_drift_pct": 0.4531,
      "n_divergent": 0,
      "threshold_pct": 1.0,
      "direction": "signed (oracle \u2212 independent)/independent; positive \u21d2 oracle over-values collateral (dangerous, alerted); negative \u21d2 oracle conservative (safe, not alerted)",
      "method": "independent NAV = min(coin spot price) \u00d7 pool get_virtual_price(); divergence vs collatOracle latestAnswer (optimistic). Alert fires only when oracle over-values by > threshold_pct."
    },
    "pegkeepers": [
      {
        "keeper": "0xF89615F75c8161dc185C03020240905f6b66bAd9",
        "pool": "0x97BA10115da528c113462EDE9C20D7adc806D93f",
        "debt": 0.0,
        "stable_symbol": "USDC",
        "stable_in_pool": 521260.35,
        "usg_in_pool": 967352.26,
        "usg_price": 0.997786
      },
      {
        "keeper": "0x8a7f16508d1e8b48bdf36023F378CC04D9506D4E",
        "pool": "0xEfc056790bb19702b2164ec6Ea6bA3AE01d81195",
        "debt": 0.0,
        "stable_symbol": "frxUSD",
        "stable_in_pool": 569733.17,
        "usg_in_pool": 1043727.75,
        "usg_price": 0.997846
      }
    ],
    "supply_composition": {
      "cdp": 2864487.86,
      "pol": 0.0,
      "susg": 709649.16,
      "cdp_pct": 80.1,
      "pol_pct": 0.0,
      "susg_pct": 19.9
    },
    "collateral_breakdown": {
      "cdp_collateral": 3509291.71,
      "pol_pool_stables": 1090993.52,
      "total": 4600285.23
    },
    "peg_defense": {
      "pol_pool_stables": 1090993.52,
      "pol_deployed": 0.0
    }
  }
}